LICENSE
MANIFEST.in
README.rst
setup.py
aino_utkik.egg-info/PKG-INFO
aino_utkik.egg-info/SOURCES.txt
aino_utkik.egg-info/dependency_links.txt
aino_utkik.egg-info/not-zip-safe
aino_utkik.egg-info/pbr.json
aino_utkik.egg-info/top_level.txt
utkik/__init__.py
utkik/base.py
utkik/decorators.py
utkik/dispatch.py
utkik/models.py
utkik/utils.py