Metadata-Version: 1.1
Name: aino-utkik
Version: 0.9.0
Summary: Small, clean code with a lazy view dispatcher and class based views for Django.
Home-page: https://github.com/aino/aino-utkik
Author: Mikko Hellsing
Author-email: mikko@aino.se
License: BSD
Platform: UNKNOWN
Classifier: Development Status :: 3 - Alpha
Classifier: Environment :: Web Environment
Classifier: Intended Audience :: Developers
Classifier: License :: OSI Approved :: BSD License
Classifier: Operating System :: OS Independent
Classifier: Programming Language :: Python :: 3 :: Only
Classifier: Topic :: Internet :: WWW/HTTP :: Dynamic Content
Classifier: Framework :: Django
